docker_pkg/__init__.py
docker_pkg/builder.py
docker_pkg/cli.py
docker_pkg/dockerfile.py
docker_pkg/drivers.py
docker_pkg/image.py
docker_pkg-4.0.4.dist-info/licenses/LICENSE
tests/__init__.py
tests/test_builder.py
tests/test_cli.py
tests/test_docker_pkg.py
tests/test_dockerfile.py
tests/test_drivers.py
tests/test_images.py
docker_pkg-4.0.4.dist-info/METADATA
docker_pkg-4.0.4.dist-info/WHEEL
docker_pkg-4.0.4.dist-info/entry_points.txt
docker_pkg-4.0.4.dist-info/top_level.txt
docker_pkg-4.0.4.dist-info/RECORD
