Metadata-Version: 2.4
Name: docker_pkg
Version: 4.0.4
Summary: Build docker images programmatically from templates.
Home-page: https://github.com/wikimedia/operations-docker-images-docker-pkg/
Author: Giuseppe Lavagetto
Author-email: joe@wikimedia.org
License: GPLv3+
Platform: GNU/Linux
Platform: BSD
Platform: MacOSX
Classifier: Environment :: Console
Classifier: Intended Audience :: System Administrators
Classifier: License :: OSI Approved :: GNU General Public License v3 or later (GPLv3+)
Classifier: Operating System :: MacOS :: MacOS X
Classifier: Operating System :: POSIX :: BSD
Classifier: Operating System :: POSIX :: Linux
Classifier: Programming Language :: Python :: 3 :: Only
Classifier: Topic :: System :: Systems Administration
License-File: LICENSE
Requires-Dist: docker<6.0.0,>=5.0.0
Requires-Dist: pyyaml>=3.11
Requires-Dist: jinja2>=2.9.6
Requires-Dist: python-debian>=0.1.30
Requires-Dist: requests<2.29
Requires-Dist: attrs
Provides-Extra: tests
Requires-Dist: coverage; extra == "tests"
Requires-Dist: pytest; extra == "tests"
Provides-Extra: doc
Requires-Dist: Sphinx; extra == "doc"
Dynamic: author
Dynamic: author-email
Dynamic: classifier
Dynamic: description
Dynamic: home-page
Dynamic: license
Dynamic: license-file
Dynamic: platform
Dynamic: provides-extra
Dynamic: requires-dist
Dynamic: summary
